src/modal_server/__init__.py
src/modal_server/server.py
orange1_modal_server-0.1.0.dist-info/METADATA
orange1_modal_server-0.1.0.dist-info/WHEEL
orange1_modal_server-0.1.0.dist-info/entry_points.txt
orange1_modal_server-0.1.0.dist-info/RECORD
