Metadata-Version: 2.4
Name: orange1-modal-server
Version: 0.1.0
Author-email: Server Modal <team@example.com>
Requires-Python: <3.13,>=3.12
Requires-Dist: httpx>=0.28.1
Requires-Dist: mcp>=1.1.1
Requires-Dist: modal>=0.67
Requires-Dist: python-dotenv>=1.0.1
